{
  "baseUrl": "https://mykinlegacy.com",
  "commit": "8967c5b65a71193fab21e02c5adfccf0beb230ba",
  "capturedAt": "2026-07-01T16:42:29.354Z",
  "notes": [
    "Internal visual review only. Do not link from public navigation.",
    "Admin pages were captured with a redacted token in the URL."
  ],
  "pages": [
    {
      "key": "home",
      "label": "Homepage",
      "path": "/",
      "screenshots": [
        {
          "pageKey": "home",
          "pageLabel": "Homepage",
          "pagePath": "/",
          "pageUrl": "https://mykinlegacy.com/",
          "viewport": {
            "key": "desktop",
            "width": 1440,
            "height": 1200
          },
          "screenshot": "home-desktop.png",
          "screenshotPath": "C:\\Users\\Administrator\\Documents\\Codex\\2026-06-29\\ai-family-crest-generator-png-png\\apps\\web\\public\\review\\full-site\\home-desktop.png",
          "dimensions": {
            "width": 1440,
            "height": 6997
          },
          "scrollHeight": 6997,
          "scrollWidth": 1440,
          "clientWidth": 1440,
          "fileSize": 5848845,
          "warnings": [],
          "failedImages": [],
          "failedRequests": [],
          "consoleErrors": [],
          "pageErrors": []
        },
        {
          "pageKey": "home",
          "pageLabel": "Homepage",
          "pagePath": "/",
          "pageUrl": "https://mykinlegacy.com/",
          "viewport": {
            "key": "tablet",
            "width": 768,
            "height": 1200
          },
          "screenshot": "home-tablet.png",
          "screenshotPath": "C:\\Users\\Administrator\\Documents\\Codex\\2026-06-29\\ai-family-crest-generator-png-png\\apps\\web\\public\\review\\full-site\\home-tablet.png",
          "dimensions": {
            "width": 768,
            "height": 9695
          },
          "scrollHeight": 9695,
          "scrollWidth": 768,
          "clientWidth": 768,
          "fileSize": 4967414,
          "warnings": [],
          "failedImages": [],
          "failedRequests": [],
          "consoleErrors": [],
          "pageErrors": []
        },
        {
          "pageKey": "home",
          "pageLabel": "Homepage",
          "pagePath": "/",
          "pageUrl": "https://mykinlegacy.com/",
          "viewport": {
            "key": "mobile",
            "width": 390,
            "height": 1200,
            "isMobile": true,
            "deviceScaleFactor": 2
          },
          "screenshot": "home-mobile.png",
          "screenshotPath": "C:\\Users\\Administrator\\Documents\\Codex\\2026-06-29\\ai-family-crest-generator-png-png\\apps\\web\\public\\review\\full-site\\home-mobile.png",
          "dimensions": {
            "width": 780,
            "height": 14502
          },
          "scrollHeight": 7251,
          "scrollWidth": 390,
          "clientWidth": 390,
          "fileSize": 6538032,
          "warnings": [],
          "failedImages": [],
          "failedRequests": [],
          "consoleErrors": [],
          "pageErrors": []
        }
      ],
      "warnings": []
    },
    {
      "key": "create",
      "label": "Create",
      "path": "/create",
      "screenshots": [
        {
          "pageKey": "create",
          "pageLabel": "Create",
          "pagePath": "/create",
          "pageUrl": "https://mykinlegacy.com/create",
          "viewport": {
            "key": "desktop",
            "width": 1440,
            "height": 1200
          },
          "screenshot": "create-desktop.png",
          "screenshotPath": "C:\\Users\\Administrator\\Documents\\Codex\\2026-06-29\\ai-family-crest-generator-png-png\\apps\\web\\public\\review\\full-site\\create-desktop.png",
          "dimensions": {
            "width": 1440,
            "height": 1896
          },
          "scrollHeight": 1896,
          "scrollWidth": 1440,
          "clientWidth": 1440,
          "fileSize": 729006,
          "warnings": [],
          "failedImages": [],
          "failedRequests": [],
          "consoleErrors": [],
          "pageErrors": []
        },
        {
          "pageKey": "create",
          "pageLabel": "Create",
          "pagePath": "/create",
          "pageUrl": "https://mykinlegacy.com/create",
          "viewport": {
            "key": "tablet",
            "width": 768,
            "height": 1200
          },
          "screenshot": "create-tablet.png",
          "screenshotPath": "C:\\Users\\Administrator\\Documents\\Codex\\2026-06-29\\ai-family-crest-generator-png-png\\apps\\web\\public\\review\\full-site\\create-tablet.png",
          "dimensions": {
            "width": 768,
            "height": 2551
          },
          "scrollHeight": 2551,
          "scrollWidth": 768,
          "clientWidth": 768,
          "fileSize": 823468,
          "warnings": [],
          "failedImages": [],
          "failedRequests": [],
          "consoleErrors": [],
          "pageErrors": []
        },
        {
          "pageKey": "create",
          "pageLabel": "Create",
          "pagePath": "/create",
          "pageUrl": "https://mykinlegacy.com/create",
          "viewport": {
            "key": "mobile",
            "width": 390,
            "height": 1200,
            "isMobile": true,
            "deviceScaleFactor": 2
          },
          "screenshot": "create-mobile.png",
          "screenshotPath": "C:\\Users\\Administrator\\Documents\\Codex\\2026-06-29\\ai-family-crest-generator-png-png\\apps\\web\\public\\review\\full-site\\create-mobile.png",
          "dimensions": {
            "width": 780,
            "height": 5090
          },
          "scrollHeight": 2545,
          "scrollWidth": 390,
          "clientWidth": 390,
          "fileSize": 1630277,
          "warnings": [],
          "failedImages": [],
          "failedRequests": [],
          "consoleErrors": [],
          "pageErrors": []
        }
      ],
      "warnings": []
    },
    {
      "key": "collection",
      "label": "Family Legacy Collection",
      "path": "/family-legacy-collection",
      "screenshots": [
        {
          "pageKey": "collection",
          "pageLabel": "Family Legacy Collection",
          "pagePath": "/family-legacy-collection",
          "pageUrl": "https://mykinlegacy.com/family-legacy-collection",
          "viewport": {
            "key": "desktop",
            "width": 1440,
            "height": 1200
          },
          "screenshot": "collection-desktop.png",
          "screenshotPath": "C:\\Users\\Administrator\\Documents\\Codex\\2026-06-29\\ai-family-crest-generator-png-png\\apps\\web\\public\\review\\full-site\\collection-desktop.png",
          "dimensions": {
            "width": 1440,
            "height": 4295
          },
          "scrollHeight": 4295,
          "scrollWidth": 1440,
          "clientWidth": 1440,
          "fileSize": 1920940,
          "warnings": [],
          "failedImages": [],
          "failedRequests": [],
          "consoleErrors": [],
          "pageErrors": []
        },
        {
          "pageKey": "collection",
          "pageLabel": "Family Legacy Collection",
          "pagePath": "/family-legacy-collection",
          "pageUrl": "https://mykinlegacy.com/family-legacy-collection",
          "viewport": {
            "key": "tablet",
            "width": 768,
            "height": 1200
          },
          "screenshot": "collection-tablet.png",
          "screenshotPath": "C:\\Users\\Administrator\\Documents\\Codex\\2026-06-29\\ai-family-crest-generator-png-png\\apps\\web\\public\\review\\full-site\\collection-tablet.png",
          "dimensions": {
            "width": 768,
            "height": 6204
          },
          "scrollHeight": 6204,
          "scrollWidth": 768,
          "clientWidth": 768,
          "fileSize": 2144056,
          "warnings": [],
          "failedImages": [],
          "failedRequests": [],
          "consoleErrors": [],
          "pageErrors": []
        },
        {
          "pageKey": "collection",
          "pageLabel": "Family Legacy Collection",
          "pagePath": "/family-legacy-collection",
          "pageUrl": "https://mykinlegacy.com/family-legacy-collection",
          "viewport": {
            "key": "mobile",
            "width": 390,
            "height": 1200,
            "isMobile": true,
            "deviceScaleFactor": 2
          },
          "screenshot": "collection-mobile.png",
          "screenshotPath": "C:\\Users\\Administrator\\Documents\\Codex\\2026-06-29\\ai-family-crest-generator-png-png\\apps\\web\\public\\review\\full-site\\collection-mobile.png",
          "dimensions": {
            "width": 780,
            "height": 12532
          },
          "scrollHeight": 6266,
          "scrollWidth": 390,
          "clientWidth": 390,
          "fileSize": 4536965,
          "warnings": [],
          "failedImages": [],
          "failedRequests": [],
          "consoleErrors": [],
          "pageErrors": []
        }
      ],
      "warnings": []
    },
    {
      "key": "interview",
      "label": "Guided Interview",
      "path": "/create/AHL-20260701-01KWEJEY",
      "screenshots": [
        {
          "pageKey": "interview",
          "pageLabel": "Guided Interview",
          "pagePath": "/create/AHL-20260701-01KWEJEY",
          "pageUrl": "https://mykinlegacy.com/create/AHL-20260701-01KWEJEY",
          "viewport": {
            "key": "desktop",
            "width": 1440,
            "height": 1200
          },
          "screenshot": "interview-desktop.png",
          "screenshotPath": "C:\\Users\\Administrator\\Documents\\Codex\\2026-06-29\\ai-family-crest-generator-png-png\\apps\\web\\public\\review\\full-site\\interview-desktop.png",
          "dimensions": {
            "width": 1440,
            "height": 1770
          },
          "scrollHeight": 1770,
          "scrollWidth": 1440,
          "clientWidth": 1440,
          "fileSize": 706847,
          "warnings": [],
          "failedImages": [],
          "failedRequests": [],
          "consoleErrors": [],
          "pageErrors": []
        },
        {
          "pageKey": "interview",
          "pageLabel": "Guided Interview",
          "pagePath": "/create/AHL-20260701-01KWEJEY",
          "pageUrl": "https://mykinlegacy.com/create/AHL-20260701-01KWEJEY",
          "viewport": {
            "key": "tablet",
            "width": 768,
            "height": 1200
          },
          "screenshot": "interview-tablet.png",
          "screenshotPath": "C:\\Users\\Administrator\\Documents\\Codex\\2026-06-29\\ai-family-crest-generator-png-png\\apps\\web\\public\\review\\full-site\\interview-tablet.png",
          "dimensions": {
            "width": 768,
            "height": 2445
          },
          "scrollHeight": 2445,
          "scrollWidth": 768,
          "clientWidth": 768,
          "fileSize": 711206,
          "warnings": [],
          "failedImages": [],
          "failedRequests": [],
          "consoleErrors": [],
          "pageErrors": []
        },
        {
          "pageKey": "interview",
          "pageLabel": "Guided Interview",
          "pagePath": "/create/AHL-20260701-01KWEJEY",
          "pageUrl": "https://mykinlegacy.com/create/AHL-20260701-01KWEJEY",
          "viewport": {
            "key": "mobile",
            "width": 390,
            "height": 1200,
            "isMobile": true,
            "deviceScaleFactor": 2
          },
          "screenshot": "interview-mobile.png",
          "screenshotPath": "C:\\Users\\Administrator\\Documents\\Codex\\2026-06-29\\ai-family-crest-generator-png-png\\apps\\web\\public\\review\\full-site\\interview-mobile.png",
          "dimensions": {
            "width": 780,
            "height": 5218
          },
          "scrollHeight": 2609,
          "scrollWidth": 390,
          "clientWidth": 390,
          "fileSize": 1478798,
          "warnings": [],
          "failedImages": [],
          "failedRequests": [],
          "consoleErrors": [],
          "pageErrors": []
        }
      ],
      "warnings": []
    },
    {
      "key": "checkout",
      "label": "Checkout",
      "path": "/checkout/AHL-20260701-01KWEJEY",
      "screenshots": [
        {
          "pageKey": "checkout",
          "pageLabel": "Checkout",
          "pagePath": "/checkout/AHL-20260701-01KWEJEY",
          "pageUrl": "https://mykinlegacy.com/checkout/AHL-20260701-01KWEJEY",
          "viewport": {
            "key": "desktop",
            "width": 1440,
            "height": 1200
          },
          "screenshot": "checkout-desktop.png",
          "screenshotPath": "C:\\Users\\Administrator\\Documents\\Codex\\2026-06-29\\ai-family-crest-generator-png-png\\apps\\web\\public\\review\\full-site\\checkout-desktop.png",
          "dimensions": {
            "width": 1440,
            "height": 2152
          },
          "scrollHeight": 2152,
          "scrollWidth": 1440,
          "clientWidth": 1440,
          "fileSize": 602484,
          "warnings": [],
          "failedImages": [],
          "failedRequests": [],
          "consoleErrors": [],
          "pageErrors": []
        },
        {
          "pageKey": "checkout",
          "pageLabel": "Checkout",
          "pagePath": "/checkout/AHL-20260701-01KWEJEY",
          "pageUrl": "https://mykinlegacy.com/checkout/AHL-20260701-01KWEJEY",
          "viewport": {
            "key": "tablet",
            "width": 768,
            "height": 1200
          },
          "screenshot": "checkout-tablet.png",
          "screenshotPath": "C:\\Users\\Administrator\\Documents\\Codex\\2026-06-29\\ai-family-crest-generator-png-png\\apps\\web\\public\\review\\full-site\\checkout-tablet.png",
          "dimensions": {
            "width": 768,
            "height": 2875
          },
          "scrollHeight": 2875,
          "scrollWidth": 768,
          "clientWidth": 768,
          "fileSize": 515276,
          "warnings": [],
          "failedImages": [],
          "failedRequests": [],
          "consoleErrors": [],
          "pageErrors": []
        },
        {
          "pageKey": "checkout",
          "pageLabel": "Checkout",
          "pagePath": "/checkout/AHL-20260701-01KWEJEY",
          "pageUrl": "https://mykinlegacy.com/checkout/AHL-20260701-01KWEJEY",
          "viewport": {
            "key": "mobile",
            "width": 390,
            "height": 1200,
            "isMobile": true,
            "deviceScaleFactor": 2
          },
          "screenshot": "checkout-mobile.png",
          "screenshotPath": "C:\\Users\\Administrator\\Documents\\Codex\\2026-06-29\\ai-family-crest-generator-png-png\\apps\\web\\public\\review\\full-site\\checkout-mobile.png",
          "dimensions": {
            "width": 780,
            "height": 6254
          },
          "scrollHeight": 3127,
          "scrollWidth": 390,
          "clientWidth": 390,
          "fileSize": 1150254,
          "warnings": [],
          "failedImages": [],
          "failedRequests": [],
          "consoleErrors": [],
          "pageErrors": []
        }
      ],
      "warnings": []
    },
    {
      "key": "payment-success",
      "label": "Payment Success",
      "path": "/payment/success?order_number=AHL-20260701-01KWEJEY",
      "screenshots": [
        {
          "pageKey": "payment-success",
          "pageLabel": "Payment Success",
          "pagePath": "/payment/success?order_number=AHL-20260701-01KWEJEY",
          "pageUrl": "https://mykinlegacy.com/payment/success?order_number=AHL-20260701-01KWEJEY",
          "viewport": {
            "key": "desktop",
            "width": 1440,
            "height": 1200
          },
          "screenshot": "payment-success-desktop.png",
          "screenshotPath": "C:\\Users\\Administrator\\Documents\\Codex\\2026-06-29\\ai-family-crest-generator-png-png\\apps\\web\\public\\review\\full-site\\payment-success-desktop.png",
          "dimensions": {
            "width": 1440,
            "height": 1521
          },
          "scrollHeight": 1521,
          "scrollWidth": 1440,
          "clientWidth": 1440,
          "fileSize": 527197,
          "warnings": [],
          "failedImages": [],
          "failedRequests": [],
          "consoleErrors": [],
          "pageErrors": []
        },
        {
          "pageKey": "payment-success",
          "pageLabel": "Payment Success",
          "pagePath": "/payment/success?order_number=AHL-20260701-01KWEJEY",
          "pageUrl": "https://mykinlegacy.com/payment/success?order_number=AHL-20260701-01KWEJEY",
          "viewport": {
            "key": "tablet",
            "width": 768,
            "height": 1200
          },
          "screenshot": "payment-success-tablet.png",
          "screenshotPath": "C:\\Users\\Administrator\\Documents\\Codex\\2026-06-29\\ai-family-crest-generator-png-png\\apps\\web\\public\\review\\full-site\\payment-success-tablet.png",
          "dimensions": {
            "width": 768,
            "height": 1521
          },
          "scrollHeight": 1521,
          "scrollWidth": 768,
          "clientWidth": 768,
          "fileSize": 347705,
          "warnings": [],
          "failedImages": [],
          "failedRequests": [],
          "consoleErrors": [],
          "pageErrors": []
        },
        {
          "pageKey": "payment-success",
          "pageLabel": "Payment Success",
          "pagePath": "/payment/success?order_number=AHL-20260701-01KWEJEY",
          "pageUrl": "https://mykinlegacy.com/payment/success?order_number=AHL-20260701-01KWEJEY",
          "viewport": {
            "key": "mobile",
            "width": 390,
            "height": 1200,
            "isMobile": true,
            "deviceScaleFactor": 2
          },
          "screenshot": "payment-success-mobile.png",
          "screenshotPath": "C:\\Users\\Administrator\\Documents\\Codex\\2026-06-29\\ai-family-crest-generator-png-png\\apps\\web\\public\\review\\full-site\\payment-success-mobile.png",
          "dimensions": {
            "width": 780,
            "height": 3144
          },
          "scrollHeight": 1572,
          "scrollWidth": 390,
          "clientWidth": 390,
          "fileSize": 638637,
          "warnings": [],
          "failedImages": [],
          "failedRequests": [],
          "consoleErrors": [],
          "pageErrors": []
        }
      ],
      "warnings": []
    },
    {
      "key": "order-status-latest",
      "label": "Order Status Latest",
      "path": "/order-status/AHL-20260701-01KWEJEY",
      "screenshots": [
        {
          "pageKey": "order-status-latest",
          "pageLabel": "Order Status Latest",
          "pagePath": "/order-status/AHL-20260701-01KWEJEY",
          "pageUrl": "https://mykinlegacy.com/order-status/AHL-20260701-01KWEJEY",
          "viewport": {
            "key": "desktop",
            "width": 1440,
            "height": 1200
          },
          "screenshot": "order-status-latest-desktop.png",
          "screenshotPath": "C:\\Users\\Administrator\\Documents\\Codex\\2026-06-29\\ai-family-crest-generator-png-png\\apps\\web\\public\\review\\full-site\\order-status-latest-desktop.png",
          "dimensions": {
            "width": 1440,
            "height": 1548
          },
          "scrollHeight": 1548,
          "scrollWidth": 1440,
          "clientWidth": 1440,
          "fileSize": 526634,
          "warnings": [],
          "failedImages": [],
          "failedRequests": [],
          "consoleErrors": [],
          "pageErrors": []
        },
        {
          "pageKey": "order-status-latest",
          "pageLabel": "Order Status Latest",
          "pagePath": "/order-status/AHL-20260701-01KWEJEY",
          "pageUrl": "https://mykinlegacy.com/order-status/AHL-20260701-01KWEJEY",
          "viewport": {
            "key": "tablet",
            "width": 768,
            "height": 1200
          },
          "screenshot": "order-status-latest-tablet.png",
          "screenshotPath": "C:\\Users\\Administrator\\Documents\\Codex\\2026-06-29\\ai-family-crest-generator-png-png\\apps\\web\\public\\review\\full-site\\order-status-latest-tablet.png",
          "dimensions": {
            "width": 768,
            "height": 2183
          },
          "scrollHeight": 2183,
          "scrollWidth": 768,
          "clientWidth": 768,
          "fileSize": 502614,
          "warnings": [],
          "failedImages": [],
          "failedRequests": [],
          "consoleErrors": [],
          "pageErrors": []
        },
        {
          "pageKey": "order-status-latest",
          "pageLabel": "Order Status Latest",
          "pagePath": "/order-status/AHL-20260701-01KWEJEY",
          "pageUrl": "https://mykinlegacy.com/order-status/AHL-20260701-01KWEJEY",
          "viewport": {
            "key": "mobile",
            "width": 390,
            "height": 1200,
            "isMobile": true,
            "deviceScaleFactor": 2
          },
          "screenshot": "order-status-latest-mobile.png",
          "screenshotPath": "C:\\Users\\Administrator\\Documents\\Codex\\2026-06-29\\ai-family-crest-generator-png-png\\apps\\web\\public\\review\\full-site\\order-status-latest-mobile.png",
          "dimensions": {
            "width": 780,
            "height": 4526
          },
          "scrollHeight": 2263,
          "scrollWidth": 390,
          "clientWidth": 390,
          "fileSize": 1112255,
          "warnings": [],
          "failedImages": [],
          "failedRequests": [],
          "consoleErrors": [],
          "pageErrors": []
        }
      ],
      "warnings": []
    },
    {
      "key": "order-status-founder",
      "label": "Order Status Founder",
      "path": "/order-status/AHL-20260701-01KWECW4",
      "screenshots": [
        {
          "pageKey": "order-status-founder",
          "pageLabel": "Order Status Founder",
          "pagePath": "/order-status/AHL-20260701-01KWECW4",
          "pageUrl": "https://mykinlegacy.com/order-status/AHL-20260701-01KWECW4",
          "viewport": {
            "key": "desktop",
            "width": 1440,
            "height": 1200
          },
          "screenshot": "order-status-founder-desktop.png",
          "screenshotPath": "C:\\Users\\Administrator\\Documents\\Codex\\2026-06-29\\ai-family-crest-generator-png-png\\apps\\web\\public\\review\\full-site\\order-status-founder-desktop.png",
          "dimensions": {
            "width": 1440,
            "height": 1548
          },
          "scrollHeight": 1548,
          "scrollWidth": 1440,
          "clientWidth": 1440,
          "fileSize": 527264,
          "warnings": [],
          "failedImages": [],
          "failedRequests": [],
          "consoleErrors": [],
          "pageErrors": []
        },
        {
          "pageKey": "order-status-founder",
          "pageLabel": "Order Status Founder",
          "pagePath": "/order-status/AHL-20260701-01KWECW4",
          "pageUrl": "https://mykinlegacy.com/order-status/AHL-20260701-01KWECW4",
          "viewport": {
            "key": "tablet",
            "width": 768,
            "height": 1200
          },
          "screenshot": "order-status-founder-tablet.png",
          "screenshotPath": "C:\\Users\\Administrator\\Documents\\Codex\\2026-06-29\\ai-family-crest-generator-png-png\\apps\\web\\public\\review\\full-site\\order-status-founder-tablet.png",
          "dimensions": {
            "width": 768,
            "height": 2183
          },
          "scrollHeight": 2183,
          "scrollWidth": 768,
          "clientWidth": 768,
          "fileSize": 503132,
          "warnings": [],
          "failedImages": [],
          "failedRequests": [
            {
              "url": "https://static.cloudflareinsights.com/beacon.min.js/v4513226cdae34746b4dedf0b4dfa099e1781791509496",
              "resourceType": "script",
              "errorText": "net::ERR_SOCKET_NOT_CONNECTED"
            }
          ],
          "consoleErrors": [
            {
              "text": "Failed to load resource: net::ERR_SOCKET_NOT_CONNECTED",
              "location": {
                "url": "https://static.cloudflareinsights.com/beacon.min.js/v4513226cdae34746b4dedf0b4dfa099e1781791509496",
                "line": 0,
                "column": 0,
                "lineNumber": 0,
                "columnNumber": 0
              }
            }
          ],
          "pageErrors": []
        },
        {
          "pageKey": "order-status-founder",
          "pageLabel": "Order Status Founder",
          "pagePath": "/order-status/AHL-20260701-01KWECW4",
          "pageUrl": "https://mykinlegacy.com/order-status/AHL-20260701-01KWECW4",
          "viewport": {
            "key": "mobile",
            "width": 390,
            "height": 1200,
            "isMobile": true,
            "deviceScaleFactor": 2
          },
          "screenshot": "order-status-founder-mobile.png",
          "screenshotPath": "C:\\Users\\Administrator\\Documents\\Codex\\2026-06-29\\ai-family-crest-generator-png-png\\apps\\web\\public\\review\\full-site\\order-status-founder-mobile.png",
          "dimensions": {
            "width": 780,
            "height": 4526
          },
          "scrollHeight": 2263,
          "scrollWidth": 390,
          "clientWidth": 390,
          "fileSize": 1113415,
          "warnings": [],
          "failedImages": [],
          "failedRequests": [],
          "consoleErrors": [],
          "pageErrors": []
        }
      ],
      "warnings": []
    },
    {
      "key": "admin-orders",
      "label": "Admin Orders",
      "path": "/admin/orders?token=[redacted]",
      "warnings": [],
      "screenshots": [
        {
          "pageKey": "admin-orders",
          "pageLabel": "Admin Orders",
          "pagePath": "/admin/orders?token=[redacted]",
          "pageUrl": "https://mykinlegacy.com/admin/orders?token=[redacted]",
          "viewport": {
            "key": "desktop",
            "width": 1440,
            "height": 1200
          },
          "screenshot": "admin-orders-desktop.png",
          "screenshotPath": "/home/runner/work/mykinlegacy/mykinlegacy/apps/web/public/review/full-site/admin-orders-desktop.png",
          "dimensions": {
            "width": 1440,
            "height": 1625
          },
          "scrollHeight": 1625,
          "scrollWidth": 1440,
          "clientWidth": 1440,
          "fileSize": 404873,
          "warnings": [],
          "failedImages": [],
          "failedRequests": [],
          "consoleErrors": [],
          "pageErrors": []
        },
        {
          "pageKey": "admin-orders",
          "pageLabel": "Admin Orders",
          "pagePath": "/admin/orders?token=[redacted]",
          "pageUrl": "https://mykinlegacy.com/admin/orders?token=[redacted]",
          "viewport": {
            "key": "tablet",
            "width": 768,
            "height": 1200
          },
          "screenshot": "admin-orders-tablet.png",
          "screenshotPath": "/home/runner/work/mykinlegacy/mykinlegacy/apps/web/public/review/full-site/admin-orders-tablet.png",
          "dimensions": {
            "width": 768,
            "height": 3410
          },
          "scrollHeight": 3410,
          "scrollWidth": 768,
          "clientWidth": 768,
          "fileSize": 547176,
          "warnings": [],
          "failedImages": [],
          "failedRequests": [],
          "consoleErrors": [],
          "pageErrors": []
        },
        {
          "pageKey": "admin-orders",
          "pageLabel": "Admin Orders",
          "pagePath": "/admin/orders?token=[redacted]",
          "pageUrl": "https://mykinlegacy.com/admin/orders?token=[redacted]",
          "viewport": {
            "key": "mobile",
            "width": 390,
            "height": 1200,
            "isMobile": true,
            "deviceScaleFactor": 2
          },
          "screenshot": "admin-orders-mobile.png",
          "screenshotPath": "/home/runner/work/mykinlegacy/mykinlegacy/apps/web/public/review/full-site/admin-orders-mobile.png",
          "dimensions": {
            "width": 780,
            "height": 7102
          },
          "scrollHeight": 3551,
          "scrollWidth": 390,
          "clientWidth": 390,
          "fileSize": 1341800,
          "warnings": [],
          "failedImages": [],
          "failedRequests": [],
          "consoleErrors": [],
          "pageErrors": []
        }
      ]
    },
    {
      "key": "admin-email-logs",
      "label": "Admin Email Logs",
      "path": "/admin/email-logs?token=[redacted]",
      "warnings": [],
      "screenshots": [
        {
          "pageKey": "admin-email-logs",
          "pageLabel": "Admin Email Logs",
          "pagePath": "/admin/email-logs?token=[redacted]",
          "pageUrl": "https://mykinlegacy.com/admin/email-logs?token=[redacted]",
          "viewport": {
            "key": "desktop",
            "width": 1440,
            "height": 1200
          },
          "screenshot": "admin-email-logs-desktop.png",
          "screenshotPath": "/home/runner/work/mykinlegacy/mykinlegacy/apps/web/public/review/full-site/admin-email-logs-desktop.png",
          "dimensions": {
            "width": 1440,
            "height": 1683
          },
          "scrollHeight": 1683,
          "scrollWidth": 1440,
          "clientWidth": 1440,
          "fileSize": 419132,
          "warnings": [],
          "failedImages": [],
          "failedRequests": [],
          "consoleErrors": [],
          "pageErrors": []
        },
        {
          "pageKey": "admin-email-logs",
          "pageLabel": "Admin Email Logs",
          "pagePath": "/admin/email-logs?token=[redacted]",
          "pageUrl": "https://mykinlegacy.com/admin/email-logs?token=[redacted]",
          "viewport": {
            "key": "tablet",
            "width": 768,
            "height": 1200
          },
          "screenshot": "admin-email-logs-tablet.png",
          "screenshotPath": "/home/runner/work/mykinlegacy/mykinlegacy/apps/web/public/review/full-site/admin-email-logs-tablet.png",
          "dimensions": {
            "width": 768,
            "height": 2818
          },
          "scrollHeight": 2818,
          "scrollWidth": 768,
          "clientWidth": 768,
          "fileSize": 486367,
          "warnings": [],
          "failedImages": [],
          "failedRequests": [],
          "consoleErrors": [],
          "pageErrors": []
        },
        {
          "pageKey": "admin-email-logs",
          "pageLabel": "Admin Email Logs",
          "pagePath": "/admin/email-logs?token=[redacted]",
          "pageUrl": "https://mykinlegacy.com/admin/email-logs?token=[redacted]",
          "viewport": {
            "key": "mobile",
            "width": 390,
            "height": 1200,
            "isMobile": true,
            "deviceScaleFactor": 2
          },
          "screenshot": "admin-email-logs-mobile.png",
          "screenshotPath": "/home/runner/work/mykinlegacy/mykinlegacy/apps/web/public/review/full-site/admin-email-logs-mobile.png",
          "dimensions": {
            "width": 780,
            "height": 6438
          },
          "scrollHeight": 3219,
          "scrollWidth": 390,
          "clientWidth": 390,
          "fileSize": 1212715,
          "warnings": [],
          "failedImages": [],
          "failedRequests": [],
          "consoleErrors": [],
          "pageErrors": []
        }
      ]
    },
    {
      "key": "admin-download-tokens",
      "label": "Admin Download Tokens",
      "path": "/admin/download-tokens?token=[redacted]",
      "warnings": [],
      "screenshots": [
        {
          "pageKey": "admin-download-tokens",
          "pageLabel": "Admin Download Tokens",
          "pagePath": "/admin/download-tokens?token=[redacted]",
          "pageUrl": "https://mykinlegacy.com/admin/download-tokens?token=[redacted]",
          "viewport": {
            "key": "desktop",
            "width": 1440,
            "height": 1200
          },
          "screenshot": "admin-download-tokens-desktop.png",
          "screenshotPath": "/home/runner/work/mykinlegacy/mykinlegacy/apps/web/public/review/full-site/admin-download-tokens-desktop.png",
          "dimensions": {
            "width": 1440,
            "height": 1521
          },
          "scrollHeight": 1521,
          "scrollWidth": 1440,
          "clientWidth": 1440,
          "fileSize": 402221,
          "warnings": [],
          "failedImages": [],
          "failedRequests": [],
          "consoleErrors": [],
          "pageErrors": []
        },
        {
          "pageKey": "admin-download-tokens",
          "pageLabel": "Admin Download Tokens",
          "pagePath": "/admin/download-tokens?token=[redacted]",
          "pageUrl": "https://mykinlegacy.com/admin/download-tokens?token=[redacted]",
          "viewport": {
            "key": "tablet",
            "width": 768,
            "height": 1200
          },
          "screenshot": "admin-download-tokens-tablet.png",
          "screenshotPath": "/home/runner/work/mykinlegacy/mykinlegacy/apps/web/public/review/full-site/admin-download-tokens-tablet.png",
          "dimensions": {
            "width": 768,
            "height": 1725
          },
          "scrollHeight": 1725,
          "scrollWidth": 768,
          "clientWidth": 768,
          "fileSize": 318729,
          "warnings": [],
          "failedImages": [],
          "failedRequests": [],
          "consoleErrors": [],
          "pageErrors": []
        },
        {
          "pageKey": "admin-download-tokens",
          "pageLabel": "Admin Download Tokens",
          "pagePath": "/admin/download-tokens?token=[redacted]",
          "pageUrl": "https://mykinlegacy.com/admin/download-tokens?token=[redacted]",
          "viewport": {
            "key": "mobile",
            "width": 390,
            "height": 1200,
            "isMobile": true,
            "deviceScaleFactor": 2
          },
          "screenshot": "admin-download-tokens-mobile.png",
          "screenshotPath": "/home/runner/work/mykinlegacy/mykinlegacy/apps/web/public/review/full-site/admin-download-tokens-mobile.png",
          "dimensions": {
            "width": 780,
            "height": 3764
          },
          "scrollHeight": 1882,
          "scrollWidth": 390,
          "clientWidth": 390,
          "fileSize": 781096,
          "warnings": [],
          "failedImages": [],
          "failedRequests": [],
          "consoleErrors": [],
          "pageErrors": []
        }
      ]
    }
  ],
  "screenshots": [
    {
      "pageKey": "home",
      "pageLabel": "Homepage",
      "pagePath": "/",
      "pageUrl": "https://mykinlegacy.com/",
      "viewport": {
        "key": "desktop",
        "width": 1440,
        "height": 1200
      },
      "screenshot": "home-desktop.png",
      "screenshotPath": "C:\\Users\\Administrator\\Documents\\Codex\\2026-06-29\\ai-family-crest-generator-png-png\\apps\\web\\public\\review\\full-site\\home-desktop.png",
      "dimensions": {
        "width": 1440,
        "height": 6997
      },
      "scrollHeight": 6997,
      "scrollWidth": 1440,
      "clientWidth": 1440,
      "fileSize": 5848845,
      "warnings": [],
      "failedImages": [],
      "failedRequests": [],
      "consoleErrors": [],
      "pageErrors": []
    },
    {
      "pageKey": "home",
      "pageLabel": "Homepage",
      "pagePath": "/",
      "pageUrl": "https://mykinlegacy.com/",
      "viewport": {
        "key": "tablet",
        "width": 768,
        "height": 1200
      },
      "screenshot": "home-tablet.png",
      "screenshotPath": "C:\\Users\\Administrator\\Documents\\Codex\\2026-06-29\\ai-family-crest-generator-png-png\\apps\\web\\public\\review\\full-site\\home-tablet.png",
      "dimensions": {
        "width": 768,
        "height": 9695
      },
      "scrollHeight": 9695,
      "scrollWidth": 768,
      "clientWidth": 768,
      "fileSize": 4967414,
      "warnings": [],
      "failedImages": [],
      "failedRequests": [],
      "consoleErrors": [],
      "pageErrors": []
    },
    {
      "pageKey": "home",
      "pageLabel": "Homepage",
      "pagePath": "/",
      "pageUrl": "https://mykinlegacy.com/",
      "viewport": {
        "key": "mobile",
        "width": 390,
        "height": 1200,
        "isMobile": true,
        "deviceScaleFactor": 2
      },
      "screenshot": "home-mobile.png",
      "screenshotPath": "C:\\Users\\Administrator\\Documents\\Codex\\2026-06-29\\ai-family-crest-generator-png-png\\apps\\web\\public\\review\\full-site\\home-mobile.png",
      "dimensions": {
        "width": 780,
        "height": 14502
      },
      "scrollHeight": 7251,
      "scrollWidth": 390,
      "clientWidth": 390,
      "fileSize": 6538032,
      "warnings": [],
      "failedImages": [],
      "failedRequests": [],
      "consoleErrors": [],
      "pageErrors": []
    },
    {
      "pageKey": "create",
      "pageLabel": "Create",
      "pagePath": "/create",
      "pageUrl": "https://mykinlegacy.com/create",
      "viewport": {
        "key": "desktop",
        "width": 1440,
        "height": 1200
      },
      "screenshot": "create-desktop.png",
      "screenshotPath": "C:\\Users\\Administrator\\Documents\\Codex\\2026-06-29\\ai-family-crest-generator-png-png\\apps\\web\\public\\review\\full-site\\create-desktop.png",
      "dimensions": {
        "width": 1440,
        "height": 1896
      },
      "scrollHeight": 1896,
      "scrollWidth": 1440,
      "clientWidth": 1440,
      "fileSize": 729006,
      "warnings": [],
      "failedImages": [],
      "failedRequests": [],
      "consoleErrors": [],
      "pageErrors": []
    },
    {
      "pageKey": "create",
      "pageLabel": "Create",
      "pagePath": "/create",
      "pageUrl": "https://mykinlegacy.com/create",
      "viewport": {
        "key": "tablet",
        "width": 768,
        "height": 1200
      },
      "screenshot": "create-tablet.png",
      "screenshotPath": "C:\\Users\\Administrator\\Documents\\Codex\\2026-06-29\\ai-family-crest-generator-png-png\\apps\\web\\public\\review\\full-site\\create-tablet.png",
      "dimensions": {
        "width": 768,
        "height": 2551
      },
      "scrollHeight": 2551,
      "scrollWidth": 768,
      "clientWidth": 768,
      "fileSize": 823468,
      "warnings": [],
      "failedImages": [],
      "failedRequests": [],
      "consoleErrors": [],
      "pageErrors": []
    },
    {
      "pageKey": "create",
      "pageLabel": "Create",
      "pagePath": "/create",
      "pageUrl": "https://mykinlegacy.com/create",
      "viewport": {
        "key": "mobile",
        "width": 390,
        "height": 1200,
        "isMobile": true,
        "deviceScaleFactor": 2
      },
      "screenshot": "create-mobile.png",
      "screenshotPath": "C:\\Users\\Administrator\\Documents\\Codex\\2026-06-29\\ai-family-crest-generator-png-png\\apps\\web\\public\\review\\full-site\\create-mobile.png",
      "dimensions": {
        "width": 780,
        "height": 5090
      },
      "scrollHeight": 2545,
      "scrollWidth": 390,
      "clientWidth": 390,
      "fileSize": 1630277,
      "warnings": [],
      "failedImages": [],
      "failedRequests": [],
      "consoleErrors": [],
      "pageErrors": []
    },
    {
      "pageKey": "collection",
      "pageLabel": "Family Legacy Collection",
      "pagePath": "/family-legacy-collection",
      "pageUrl": "https://mykinlegacy.com/family-legacy-collection",
      "viewport": {
        "key": "desktop",
        "width": 1440,
        "height": 1200
      },
      "screenshot": "collection-desktop.png",
      "screenshotPath": "C:\\Users\\Administrator\\Documents\\Codex\\2026-06-29\\ai-family-crest-generator-png-png\\apps\\web\\public\\review\\full-site\\collection-desktop.png",
      "dimensions": {
        "width": 1440,
        "height": 4295
      },
      "scrollHeight": 4295,
      "scrollWidth": 1440,
      "clientWidth": 1440,
      "fileSize": 1920940,
      "warnings": [],
      "failedImages": [],
      "failedRequests": [],
      "consoleErrors": [],
      "pageErrors": []
    },
    {
      "pageKey": "collection",
      "pageLabel": "Family Legacy Collection",
      "pagePath": "/family-legacy-collection",
      "pageUrl": "https://mykinlegacy.com/family-legacy-collection",
      "viewport": {
        "key": "tablet",
        "width": 768,
        "height": 1200
      },
      "screenshot": "collection-tablet.png",
      "screenshotPath": "C:\\Users\\Administrator\\Documents\\Codex\\2026-06-29\\ai-family-crest-generator-png-png\\apps\\web\\public\\review\\full-site\\collection-tablet.png",
      "dimensions": {
        "width": 768,
        "height": 6204
      },
      "scrollHeight": 6204,
      "scrollWidth": 768,
      "clientWidth": 768,
      "fileSize": 2144056,
      "warnings": [],
      "failedImages": [],
      "failedRequests": [],
      "consoleErrors": [],
      "pageErrors": []
    },
    {
      "pageKey": "collection",
      "pageLabel": "Family Legacy Collection",
      "pagePath": "/family-legacy-collection",
      "pageUrl": "https://mykinlegacy.com/family-legacy-collection",
      "viewport": {
        "key": "mobile",
        "width": 390,
        "height": 1200,
        "isMobile": true,
        "deviceScaleFactor": 2
      },
      "screenshot": "collection-mobile.png",
      "screenshotPath": "C:\\Users\\Administrator\\Documents\\Codex\\2026-06-29\\ai-family-crest-generator-png-png\\apps\\web\\public\\review\\full-site\\collection-mobile.png",
      "dimensions": {
        "width": 780,
        "height": 12532
      },
      "scrollHeight": 6266,
      "scrollWidth": 390,
      "clientWidth": 390,
      "fileSize": 4536965,
      "warnings": [],
      "failedImages": [],
      "failedRequests": [],
      "consoleErrors": [],
      "pageErrors": []
    },
    {
      "pageKey": "interview",
      "pageLabel": "Guided Interview",
      "pagePath": "/create/AHL-20260701-01KWEJEY",
      "pageUrl": "https://mykinlegacy.com/create/AHL-20260701-01KWEJEY",
      "viewport": {
        "key": "desktop",
        "width": 1440,
        "height": 1200
      },
      "screenshot": "interview-desktop.png",
      "screenshotPath": "C:\\Users\\Administrator\\Documents\\Codex\\2026-06-29\\ai-family-crest-generator-png-png\\apps\\web\\public\\review\\full-site\\interview-desktop.png",
      "dimensions": {
        "width": 1440,
        "height": 1770
      },
      "scrollHeight": 1770,
      "scrollWidth": 1440,
      "clientWidth": 1440,
      "fileSize": 706847,
      "warnings": [],
      "failedImages": [],
      "failedRequests": [],
      "consoleErrors": [],
      "pageErrors": []
    },
    {
      "pageKey": "interview",
      "pageLabel": "Guided Interview",
      "pagePath": "/create/AHL-20260701-01KWEJEY",
      "pageUrl": "https://mykinlegacy.com/create/AHL-20260701-01KWEJEY",
      "viewport": {
        "key": "tablet",
        "width": 768,
        "height": 1200
      },
      "screenshot": "interview-tablet.png",
      "screenshotPath": "C:\\Users\\Administrator\\Documents\\Codex\\2026-06-29\\ai-family-crest-generator-png-png\\apps\\web\\public\\review\\full-site\\interview-tablet.png",
      "dimensions": {
        "width": 768,
        "height": 2445
      },
      "scrollHeight": 2445,
      "scrollWidth": 768,
      "clientWidth": 768,
      "fileSize": 711206,
      "warnings": [],
      "failedImages": [],
      "failedRequests": [],
      "consoleErrors": [],
      "pageErrors": []
    },
    {
      "pageKey": "interview",
      "pageLabel": "Guided Interview",
      "pagePath": "/create/AHL-20260701-01KWEJEY",
      "pageUrl": "https://mykinlegacy.com/create/AHL-20260701-01KWEJEY",
      "viewport": {
        "key": "mobile",
        "width": 390,
        "height": 1200,
        "isMobile": true,
        "deviceScaleFactor": 2
      },
      "screenshot": "interview-mobile.png",
      "screenshotPath": "C:\\Users\\Administrator\\Documents\\Codex\\2026-06-29\\ai-family-crest-generator-png-png\\apps\\web\\public\\review\\full-site\\interview-mobile.png",
      "dimensions": {
        "width": 780,
        "height": 5218
      },
      "scrollHeight": 2609,
      "scrollWidth": 390,
      "clientWidth": 390,
      "fileSize": 1478798,
      "warnings": [],
      "failedImages": [],
      "failedRequests": [],
      "consoleErrors": [],
      "pageErrors": []
    },
    {
      "pageKey": "checkout",
      "pageLabel": "Checkout",
      "pagePath": "/checkout/AHL-20260701-01KWEJEY",
      "pageUrl": "https://mykinlegacy.com/checkout/AHL-20260701-01KWEJEY",
      "viewport": {
        "key": "desktop",
        "width": 1440,
        "height": 1200
      },
      "screenshot": "checkout-desktop.png",
      "screenshotPath": "C:\\Users\\Administrator\\Documents\\Codex\\2026-06-29\\ai-family-crest-generator-png-png\\apps\\web\\public\\review\\full-site\\checkout-desktop.png",
      "dimensions": {
        "width": 1440,
        "height": 2152
      },
      "scrollHeight": 2152,
      "scrollWidth": 1440,
      "clientWidth": 1440,
      "fileSize": 602484,
      "warnings": [],
      "failedImages": [],
      "failedRequests": [],
      "consoleErrors": [],
      "pageErrors": []
    },
    {
      "pageKey": "checkout",
      "pageLabel": "Checkout",
      "pagePath": "/checkout/AHL-20260701-01KWEJEY",
      "pageUrl": "https://mykinlegacy.com/checkout/AHL-20260701-01KWEJEY",
      "viewport": {
        "key": "tablet",
        "width": 768,
        "height": 1200
      },
      "screenshot": "checkout-tablet.png",
      "screenshotPath": "C:\\Users\\Administrator\\Documents\\Codex\\2026-06-29\\ai-family-crest-generator-png-png\\apps\\web\\public\\review\\full-site\\checkout-tablet.png",
      "dimensions": {
        "width": 768,
        "height": 2875
      },
      "scrollHeight": 2875,
      "scrollWidth": 768,
      "clientWidth": 768,
      "fileSize": 515276,
      "warnings": [],
      "failedImages": [],
      "failedRequests": [],
      "consoleErrors": [],
      "pageErrors": []
    },
    {
      "pageKey": "checkout",
      "pageLabel": "Checkout",
      "pagePath": "/checkout/AHL-20260701-01KWEJEY",
      "pageUrl": "https://mykinlegacy.com/checkout/AHL-20260701-01KWEJEY",
      "viewport": {
        "key": "mobile",
        "width": 390,
        "height": 1200,
        "isMobile": true,
        "deviceScaleFactor": 2
      },
      "screenshot": "checkout-mobile.png",
      "screenshotPath": "C:\\Users\\Administrator\\Documents\\Codex\\2026-06-29\\ai-family-crest-generator-png-png\\apps\\web\\public\\review\\full-site\\checkout-mobile.png",
      "dimensions": {
        "width": 780,
        "height": 6254
      },
      "scrollHeight": 3127,
      "scrollWidth": 390,
      "clientWidth": 390,
      "fileSize": 1150254,
      "warnings": [],
      "failedImages": [],
      "failedRequests": [],
      "consoleErrors": [],
      "pageErrors": []
    },
    {
      "pageKey": "payment-success",
      "pageLabel": "Payment Success",
      "pagePath": "/payment/success?order_number=AHL-20260701-01KWEJEY",
      "pageUrl": "https://mykinlegacy.com/payment/success?order_number=AHL-20260701-01KWEJEY",
      "viewport": {
        "key": "desktop",
        "width": 1440,
        "height": 1200
      },
      "screenshot": "payment-success-desktop.png",
      "screenshotPath": "C:\\Users\\Administrator\\Documents\\Codex\\2026-06-29\\ai-family-crest-generator-png-png\\apps\\web\\public\\review\\full-site\\payment-success-desktop.png",
      "dimensions": {
        "width": 1440,
        "height": 1521
      },
      "scrollHeight": 1521,
      "scrollWidth": 1440,
      "clientWidth": 1440,
      "fileSize": 527197,
      "warnings": [],
      "failedImages": [],
      "failedRequests": [],
      "consoleErrors": [],
      "pageErrors": []
    },
    {
      "pageKey": "payment-success",
      "pageLabel": "Payment Success",
      "pagePath": "/payment/success?order_number=AHL-20260701-01KWEJEY",
      "pageUrl": "https://mykinlegacy.com/payment/success?order_number=AHL-20260701-01KWEJEY",
      "viewport": {
        "key": "tablet",
        "width": 768,
        "height": 1200
      },
      "screenshot": "payment-success-tablet.png",
      "screenshotPath": "C:\\Users\\Administrator\\Documents\\Codex\\2026-06-29\\ai-family-crest-generator-png-png\\apps\\web\\public\\review\\full-site\\payment-success-tablet.png",
      "dimensions": {
        "width": 768,
        "height": 1521
      },
      "scrollHeight": 1521,
      "scrollWidth": 768,
      "clientWidth": 768,
      "fileSize": 347705,
      "warnings": [],
      "failedImages": [],
      "failedRequests": [],
      "consoleErrors": [],
      "pageErrors": []
    },
    {
      "pageKey": "payment-success",
      "pageLabel": "Payment Success",
      "pagePath": "/payment/success?order_number=AHL-20260701-01KWEJEY",
      "pageUrl": "https://mykinlegacy.com/payment/success?order_number=AHL-20260701-01KWEJEY",
      "viewport": {
        "key": "mobile",
        "width": 390,
        "height": 1200,
        "isMobile": true,
        "deviceScaleFactor": 2
      },
      "screenshot": "payment-success-mobile.png",
      "screenshotPath": "C:\\Users\\Administrator\\Documents\\Codex\\2026-06-29\\ai-family-crest-generator-png-png\\apps\\web\\public\\review\\full-site\\payment-success-mobile.png",
      "dimensions": {
        "width": 780,
        "height": 3144
      },
      "scrollHeight": 1572,
      "scrollWidth": 390,
      "clientWidth": 390,
      "fileSize": 638637,
      "warnings": [],
      "failedImages": [],
      "failedRequests": [],
      "consoleErrors": [],
      "pageErrors": []
    },
    {
      "pageKey": "order-status-latest",
      "pageLabel": "Order Status Latest",
      "pagePath": "/order-status/AHL-20260701-01KWEJEY",
      "pageUrl": "https://mykinlegacy.com/order-status/AHL-20260701-01KWEJEY",
      "viewport": {
        "key": "desktop",
        "width": 1440,
        "height": 1200
      },
      "screenshot": "order-status-latest-desktop.png",
      "screenshotPath": "C:\\Users\\Administrator\\Documents\\Codex\\2026-06-29\\ai-family-crest-generator-png-png\\apps\\web\\public\\review\\full-site\\order-status-latest-desktop.png",
      "dimensions": {
        "width": 1440,
        "height": 1548
      },
      "scrollHeight": 1548,
      "scrollWidth": 1440,
      "clientWidth": 1440,
      "fileSize": 526634,
      "warnings": [],
      "failedImages": [],
      "failedRequests": [],
      "consoleErrors": [],
      "pageErrors": []
    },
    {
      "pageKey": "order-status-latest",
      "pageLabel": "Order Status Latest",
      "pagePath": "/order-status/AHL-20260701-01KWEJEY",
      "pageUrl": "https://mykinlegacy.com/order-status/AHL-20260701-01KWEJEY",
      "viewport": {
        "key": "tablet",
        "width": 768,
        "height": 1200
      },
      "screenshot": "order-status-latest-tablet.png",
      "screenshotPath": "C:\\Users\\Administrator\\Documents\\Codex\\2026-06-29\\ai-family-crest-generator-png-png\\apps\\web\\public\\review\\full-site\\order-status-latest-tablet.png",
      "dimensions": {
        "width": 768,
        "height": 2183
      },
      "scrollHeight": 2183,
      "scrollWidth": 768,
      "clientWidth": 768,
      "fileSize": 502614,
      "warnings": [],
      "failedImages": [],
      "failedRequests": [],
      "consoleErrors": [],
      "pageErrors": []
    },
    {
      "pageKey": "order-status-latest",
      "pageLabel": "Order Status Latest",
      "pagePath": "/order-status/AHL-20260701-01KWEJEY",
      "pageUrl": "https://mykinlegacy.com/order-status/AHL-20260701-01KWEJEY",
      "viewport": {
        "key": "mobile",
        "width": 390,
        "height": 1200,
        "isMobile": true,
        "deviceScaleFactor": 2
      },
      "screenshot": "order-status-latest-mobile.png",
      "screenshotPath": "C:\\Users\\Administrator\\Documents\\Codex\\2026-06-29\\ai-family-crest-generator-png-png\\apps\\web\\public\\review\\full-site\\order-status-latest-mobile.png",
      "dimensions": {
        "width": 780,
        "height": 4526
      },
      "scrollHeight": 2263,
      "scrollWidth": 390,
      "clientWidth": 390,
      "fileSize": 1112255,
      "warnings": [],
      "failedImages": [],
      "failedRequests": [],
      "consoleErrors": [],
      "pageErrors": []
    },
    {
      "pageKey": "order-status-founder",
      "pageLabel": "Order Status Founder",
      "pagePath": "/order-status/AHL-20260701-01KWECW4",
      "pageUrl": "https://mykinlegacy.com/order-status/AHL-20260701-01KWECW4",
      "viewport": {
        "key": "desktop",
        "width": 1440,
        "height": 1200
      },
      "screenshot": "order-status-founder-desktop.png",
      "screenshotPath": "C:\\Users\\Administrator\\Documents\\Codex\\2026-06-29\\ai-family-crest-generator-png-png\\apps\\web\\public\\review\\full-site\\order-status-founder-desktop.png",
      "dimensions": {
        "width": 1440,
        "height": 1548
      },
      "scrollHeight": 1548,
      "scrollWidth": 1440,
      "clientWidth": 1440,
      "fileSize": 527264,
      "warnings": [],
      "failedImages": [],
      "failedRequests": [],
      "consoleErrors": [],
      "pageErrors": []
    },
    {
      "pageKey": "order-status-founder",
      "pageLabel": "Order Status Founder",
      "pagePath": "/order-status/AHL-20260701-01KWECW4",
      "pageUrl": "https://mykinlegacy.com/order-status/AHL-20260701-01KWECW4",
      "viewport": {
        "key": "tablet",
        "width": 768,
        "height": 1200
      },
      "screenshot": "order-status-founder-tablet.png",
      "screenshotPath": "C:\\Users\\Administrator\\Documents\\Codex\\2026-06-29\\ai-family-crest-generator-png-png\\apps\\web\\public\\review\\full-site\\order-status-founder-tablet.png",
      "dimensions": {
        "width": 768,
        "height": 2183
      },
      "scrollHeight": 2183,
      "scrollWidth": 768,
      "clientWidth": 768,
      "fileSize": 503132,
      "warnings": [],
      "failedImages": [],
      "failedRequests": [
        {
          "url": "https://static.cloudflareinsights.com/beacon.min.js/v4513226cdae34746b4dedf0b4dfa099e1781791509496",
          "resourceType": "script",
          "errorText": "net::ERR_SOCKET_NOT_CONNECTED"
        }
      ],
      "consoleErrors": [
        {
          "text": "Failed to load resource: net::ERR_SOCKET_NOT_CONNECTED",
          "location": {
            "url": "https://static.cloudflareinsights.com/beacon.min.js/v4513226cdae34746b4dedf0b4dfa099e1781791509496",
            "line": 0,
            "column": 0,
            "lineNumber": 0,
            "columnNumber": 0
          }
        }
      ],
      "pageErrors": []
    },
    {
      "pageKey": "order-status-founder",
      "pageLabel": "Order Status Founder",
      "pagePath": "/order-status/AHL-20260701-01KWECW4",
      "pageUrl": "https://mykinlegacy.com/order-status/AHL-20260701-01KWECW4",
      "viewport": {
        "key": "mobile",
        "width": 390,
        "height": 1200,
        "isMobile": true,
        "deviceScaleFactor": 2
      },
      "screenshot": "order-status-founder-mobile.png",
      "screenshotPath": "C:\\Users\\Administrator\\Documents\\Codex\\2026-06-29\\ai-family-crest-generator-png-png\\apps\\web\\public\\review\\full-site\\order-status-founder-mobile.png",
      "dimensions": {
        "width": 780,
        "height": 4526
      },
      "scrollHeight": 2263,
      "scrollWidth": 390,
      "clientWidth": 390,
      "fileSize": 1113415,
      "warnings": [],
      "failedImages": [],
      "failedRequests": [],
      "consoleErrors": [],
      "pageErrors": []
    },
    {
      "pageKey": "admin-orders",
      "pageLabel": "Admin Orders",
      "pagePath": "/admin/orders?token=[redacted]",
      "pageUrl": "https://mykinlegacy.com/admin/orders?token=[redacted]",
      "viewport": {
        "key": "desktop",
        "width": 1440,
        "height": 1200
      },
      "screenshot": "admin-orders-desktop.png",
      "screenshotPath": "/home/runner/work/mykinlegacy/mykinlegacy/apps/web/public/review/full-site/admin-orders-desktop.png",
      "dimensions": {
        "width": 1440,
        "height": 1625
      },
      "scrollHeight": 1625,
      "scrollWidth": 1440,
      "clientWidth": 1440,
      "fileSize": 404873,
      "warnings": [],
      "failedImages": [],
      "failedRequests": [],
      "consoleErrors": [],
      "pageErrors": []
    },
    {
      "pageKey": "admin-orders",
      "pageLabel": "Admin Orders",
      "pagePath": "/admin/orders?token=[redacted]",
      "pageUrl": "https://mykinlegacy.com/admin/orders?token=[redacted]",
      "viewport": {
        "key": "tablet",
        "width": 768,
        "height": 1200
      },
      "screenshot": "admin-orders-tablet.png",
      "screenshotPath": "/home/runner/work/mykinlegacy/mykinlegacy/apps/web/public/review/full-site/admin-orders-tablet.png",
      "dimensions": {
        "width": 768,
        "height": 3410
      },
      "scrollHeight": 3410,
      "scrollWidth": 768,
      "clientWidth": 768,
      "fileSize": 547176,
      "warnings": [],
      "failedImages": [],
      "failedRequests": [],
      "consoleErrors": [],
      "pageErrors": []
    },
    {
      "pageKey": "admin-orders",
      "pageLabel": "Admin Orders",
      "pagePath": "/admin/orders?token=[redacted]",
      "pageUrl": "https://mykinlegacy.com/admin/orders?token=[redacted]",
      "viewport": {
        "key": "mobile",
        "width": 390,
        "height": 1200,
        "isMobile": true,
        "deviceScaleFactor": 2
      },
      "screenshot": "admin-orders-mobile.png",
      "screenshotPath": "/home/runner/work/mykinlegacy/mykinlegacy/apps/web/public/review/full-site/admin-orders-mobile.png",
      "dimensions": {
        "width": 780,
        "height": 7102
      },
      "scrollHeight": 3551,
      "scrollWidth": 390,
      "clientWidth": 390,
      "fileSize": 1341800,
      "warnings": [],
      "failedImages": [],
      "failedRequests": [],
      "consoleErrors": [],
      "pageErrors": []
    },
    {
      "pageKey": "admin-email-logs",
      "pageLabel": "Admin Email Logs",
      "pagePath": "/admin/email-logs?token=[redacted]",
      "pageUrl": "https://mykinlegacy.com/admin/email-logs?token=[redacted]",
      "viewport": {
        "key": "desktop",
        "width": 1440,
        "height": 1200
      },
      "screenshot": "admin-email-logs-desktop.png",
      "screenshotPath": "/home/runner/work/mykinlegacy/mykinlegacy/apps/web/public/review/full-site/admin-email-logs-desktop.png",
      "dimensions": {
        "width": 1440,
        "height": 1683
      },
      "scrollHeight": 1683,
      "scrollWidth": 1440,
      "clientWidth": 1440,
      "fileSize": 419132,
      "warnings": [],
      "failedImages": [],
      "failedRequests": [],
      "consoleErrors": [],
      "pageErrors": []
    },
    {
      "pageKey": "admin-email-logs",
      "pageLabel": "Admin Email Logs",
      "pagePath": "/admin/email-logs?token=[redacted]",
      "pageUrl": "https://mykinlegacy.com/admin/email-logs?token=[redacted]",
      "viewport": {
        "key": "tablet",
        "width": 768,
        "height": 1200
      },
      "screenshot": "admin-email-logs-tablet.png",
      "screenshotPath": "/home/runner/work/mykinlegacy/mykinlegacy/apps/web/public/review/full-site/admin-email-logs-tablet.png",
      "dimensions": {
        "width": 768,
        "height": 2818
      },
      "scrollHeight": 2818,
      "scrollWidth": 768,
      "clientWidth": 768,
      "fileSize": 486367,
      "warnings": [],
      "failedImages": [],
      "failedRequests": [],
      "consoleErrors": [],
      "pageErrors": []
    },
    {
      "pageKey": "admin-email-logs",
      "pageLabel": "Admin Email Logs",
      "pagePath": "/admin/email-logs?token=[redacted]",
      "pageUrl": "https://mykinlegacy.com/admin/email-logs?token=[redacted]",
      "viewport": {
        "key": "mobile",
        "width": 390,
        "height": 1200,
        "isMobile": true,
        "deviceScaleFactor": 2
      },
      "screenshot": "admin-email-logs-mobile.png",
      "screenshotPath": "/home/runner/work/mykinlegacy/mykinlegacy/apps/web/public/review/full-site/admin-email-logs-mobile.png",
      "dimensions": {
        "width": 780,
        "height": 6438
      },
      "scrollHeight": 3219,
      "scrollWidth": 390,
      "clientWidth": 390,
      "fileSize": 1212715,
      "warnings": [],
      "failedImages": [],
      "failedRequests": [],
      "consoleErrors": [],
      "pageErrors": []
    },
    {
      "pageKey": "admin-download-tokens",
      "pageLabel": "Admin Download Tokens",
      "pagePath": "/admin/download-tokens?token=[redacted]",
      "pageUrl": "https://mykinlegacy.com/admin/download-tokens?token=[redacted]",
      "viewport": {
        "key": "desktop",
        "width": 1440,
        "height": 1200
      },
      "screenshot": "admin-download-tokens-desktop.png",
      "screenshotPath": "/home/runner/work/mykinlegacy/mykinlegacy/apps/web/public/review/full-site/admin-download-tokens-desktop.png",
      "dimensions": {
        "width": 1440,
        "height": 1521
      },
      "scrollHeight": 1521,
      "scrollWidth": 1440,
      "clientWidth": 1440,
      "fileSize": 402221,
      "warnings": [],
      "failedImages": [],
      "failedRequests": [],
      "consoleErrors": [],
      "pageErrors": []
    },
    {
      "pageKey": "admin-download-tokens",
      "pageLabel": "Admin Download Tokens",
      "pagePath": "/admin/download-tokens?token=[redacted]",
      "pageUrl": "https://mykinlegacy.com/admin/download-tokens?token=[redacted]",
      "viewport": {
        "key": "tablet",
        "width": 768,
        "height": 1200
      },
      "screenshot": "admin-download-tokens-tablet.png",
      "screenshotPath": "/home/runner/work/mykinlegacy/mykinlegacy/apps/web/public/review/full-site/admin-download-tokens-tablet.png",
      "dimensions": {
        "width": 768,
        "height": 1725
      },
      "scrollHeight": 1725,
      "scrollWidth": 768,
      "clientWidth": 768,
      "fileSize": 318729,
      "warnings": [],
      "failedImages": [],
      "failedRequests": [],
      "consoleErrors": [],
      "pageErrors": []
    },
    {
      "pageKey": "admin-download-tokens",
      "pageLabel": "Admin Download Tokens",
      "pagePath": "/admin/download-tokens?token=[redacted]",
      "pageUrl": "https://mykinlegacy.com/admin/download-tokens?token=[redacted]",
      "viewport": {
        "key": "mobile",
        "width": 390,
        "height": 1200,
        "isMobile": true,
        "deviceScaleFactor": 2
      },
      "screenshot": "admin-download-tokens-mobile.png",
      "screenshotPath": "/home/runner/work/mykinlegacy/mykinlegacy/apps/web/public/review/full-site/admin-download-tokens-mobile.png",
      "dimensions": {
        "width": 780,
        "height": 3764
      },
      "scrollHeight": 1882,
      "scrollWidth": 390,
      "clientWidth": 390,
      "fileSize": 781096,
      "warnings": [],
      "failedImages": [],
      "failedRequests": [],
      "consoleErrors": [],
      "pageErrors": []
    }
  ]
}
